AUTHORS
CHANGES
LICENSE
MANIFEST.in
README.rst
setup.cfg
setup.py
docs/Makefile
docs/conf.py
docs/configure.rst
docs/contributing.rst
docs/index.rst
docs/make.bat
docs/pipeline.rst
docs/reference.rst
docs/tcp.rst
docs/timing.rst
docs/types.rst
statsd/__init__.py
statsd/client.py
statsd/tests.py
statsd/defaults/__init__.py
statsd/defaults/django.py
statsd/defaults/env.py
statsd_exporter.egg-info/PKG-INFO
statsd_exporter.egg-info/SOURCES.txt
statsd_exporter.egg-info/dependency_links.txt
statsd_exporter.egg-info/top_level.txt